prosessilouhinta/__init__.py
prosessilouhinta/__main__.py
prosessilouhinta/cli.py
prosessilouhinta/cpa.py
prosessilouhinta/prosessilouhinta.py
prosessilouhinta-2022.11.13.dist-info/LICENSE
prosessilouhinta-2022.11.13.dist-info/METADATA
prosessilouhinta-2022.11.13.dist-info/WHEEL
prosessilouhinta-2022.11.13.dist-info/entry_points.txt
prosessilouhinta-2022.11.13.dist-info/top_level.txt
prosessilouhinta-2022.11.13.dist-info/RECORD
