Metadata-Version: 2.1
Name: prosessilouhinta
Version: 2022.11.13
Summary: Process mining (Finnish prosessilouhinta) from eventlogs.
Author-email: Stefan Hagen <stefan@hagen.link>
Maintainer-email: Stefan Hagen <stefan@hagen.link>
Project-URL: Homepage, https://git.sr.ht/~sthagen/prosessilouhinta
Project-URL: Bug-Tracker, https://todo.sr.ht/~sthagen/prosessilouhinta
Project-URL: Documentation, https://codes.dilettant.life/docs/prosessilouhinta
Project-URL: Source-Code, https://git.sr.ht/~sthagen/prosessilouhinta
Project-URL: Test-Coverage, https://codes.dilettant.life/coverage/prosessilouhinta
Keywords: developer-tools,process-mining
Classifier: Development Status :: 3 - Alpha
Classifier: Intended Audience :: Developers
Classifier: License :: OSI Approved :: MIT License
Classifier: Programming Language :: Python :: 3.9
Classifier: Programming Language :: Python :: 3.10
Classifier: Programming Language :: Python :: 3.11
Requires-Python: >=3.9
License-File: LICENSE
Requires-Dist: typer (>=0.7.0)
Provides-Extra: dev
Requires-Dist: black ; extra == 'dev'
Requires-Dist: coverage ; extra == 'dev'
Requires-Dist: flake8 ; extra == 'dev'
Requires-Dist: hypothesis ; extra == 'dev'
Requires-Dist: mypy ; extra == 'dev'
Requires-Dist: pytest ; extra == 'dev'
Requires-Dist: pytest-cov ; extra == 'dev'
Requires-Dist: pytest-flake8 ; extra == 'dev'
